[
    {
        "aliases": ["s01"],
        "name": "Karate Chop",
        "level": 1,
        "cd": 6,
        "type": "melee",
        "desc": "Machamp attacks in a straight line dealing damage to enemies hit.",
        "fields": [
            {
                "title": "Damage",
                "value": "217% Atk + 17 x (Level - 1) + 320",
                "calc_variables": {
                    "atk_modifier": 2.17,
                    "lvl_modifier": 17,
                    "addend": 320
                },
                "type": "inline"
            }
        ]
    },
    {
        "aliases": ["s02", "bu"],
        "name": "Bulk Up",
        "level": 1,
        "cd": 9,
        "type": "buff",
        "desc": "Machamp buffs themselves for 3s increasing attack by 15%. Machamp is unstoppable for the duration and gains 40% attack speed and movement speed for 3s. Machamp’s next auto attack is boosted."
    },
    {
        "aliases": ["s11", "punch", "dp"],
        "name": "Dynamic Punch",
        "level": 5,
        "cd": 8,
        "type": "hindrance",
        "desc": "Machamp jumps to target location, briefly stunning enemies hit, slowing them by 40% for 3s, and dealing damage four times in quick succession to the landing radius. Machamp’s Atk is increased by 15% and gains bonus movement speed for 6s when using Dynamic Punch.",
        "fields": [
            {
                "title": "Damage - Per Tick (4 Ticks)",
                "value": "28% Atk + 1 x (Level - 1) + 50",
                "calc_variables": {
                    "atk_modifier": 0.28,
                    "lvl_modifier": 1,
                    "addend": 50
                },
                "type": "inline"
            },
            {
                "title": "Level 11",
                "value": "Further increases movement speed and Atk bonus by 5%.",
                "type": "data"
            }
        ]
    },
    {
        "aliases": ["s12", "sub"],
        "name": "Submission",
        "level": 5,
        "cd": 9,
        "type": "buff",
        "desc": "Machamp becomes unstoppable and gains 50% increased movement speed for 5s or until the next auto attack. Machamp’s next auto attack during submission is enhanced, hitting twice and slamming the target down behind Machamp. If this attack hits, Machamp also gains 5% increased Critical-Hit Rate and 50% Attack Speed for 3s.",
        "fields": [
            {
                "title": "Damage - 2x",
                "value": "91% Atk + 4 x (Level - 1) + 170",
                "calc_variables": {
                    "atk_modifier": 0.91,
                    "lvl_modifier": 4,
                    "addend": 170
                },
                "type": "inline"
            },
            {
                "title": "Level 11",
                "value": "Further increases Critical-Hit Rate by 5% and Attack Speed by 10%.",
                "type": "data"
            }
        ]
    },
    {
        "aliases": ["s21", "cc"],
        "name": "Close Combat",
        "level": 7,
        "cd": 6,
        "type": "melee",
        "desc": "Machamp unleashes a barrage of blows in a targeted direction, hitting multiple times and finishing with a single large strike. Machamp is unstoppable for the duration and can move while using close combat.",
        "fields": [
            {
                "title": "Damage - Per Hit (4 Hits)",
                "value": "59% Atk + 2 x (Level - 1) + 50",
                "calc_variables": {
                    "atk_modifier": 0.59,
                    "lvl_modifier": 2,
                    "addend": 50
                },
                "type": "inline"
            },
            {
                "title": "Damage - Final Hit",
                "value": "177% Atk + 6 x (Level - 1) + 150",
                "calc_variables": {
                    "atk_modifier": 1.77,
                    "lvl_modifier": 6,
                    "addend": 150
                },
                "type": "inline"
            },
            {
                "title": "Level 13",
                "value": "Deals 25% additional damage if the target is affected by a status condition.",
                "type": "data"
            }
        ]
    },
    {
        "aliases": ["s22", "chop"],
        "name": "Cross Chop",
        "level": 7,
        "cd": 6,
        "type": "melee",
        "desc": "Machamp dashes forward dealing damage to enemies hit. Cross chop increases Critical-Hit Rate by 5% for 3s and can critically strike.",
        "fields": [
            {
                "title": "Damage",
                "value": "98% Atk + 13 x (Level - 1) + 290",
                "calc_variables": {
                    "atk_modifier": 0.98,
                    "lvl_modifier": 13,
                    "addend": 290
                },
                "type": "inline"
            },
            {
                "title": "Level 13",
                "value": "Machamp’s auto attacks increases Atk by 2, permanently stacking up to 40 times.",
                "type": "data"
            }
        ]
    },
    {
        "aliases": ["u", "unite"],
        "name": "Barrage Blow",
        "level": 9,
        "cd": 134,
        "type": "buff",
        "desc": "Increases Machamp's movement speed, Attack by 30%, Defense by 200, and Sp. Defense by 200 for 10s. If used again, unleash a combo attack, dealing damage to enemies in the area of effect and shoving them. The final blow deals double the damage of the previous hits.",
        "fields": [
            {
                "title": "Damage - 6 Hits",
                "value": "100% Atk + 2 x (Level - 1) + 100",
                "calc_variables": {
                    "atk_modifier": 1,
                    "lvl_modifier": 2,
                    "addend": 100
                },
                "type": "inline"
            },
            {
                "title": "Damage - Final Hit",
                "value": "200% Atk + 4 x (Level - 1) + 200",
                "calc_variables": {
                    "atk_modifier": 2,
                    "lvl_modifier": 4,
                    "addend": 200
                },
                "type": "inline"
            }
        ]
    }
]